pysat_kamodo/__init__.py
pysat_kamodo/pysat_kamodo.py
pysat_kamodo-0.0.1.dist-info/LICENSE
pysat_kamodo-0.0.1.dist-info/METADATA
pysat_kamodo-0.0.1.dist-info/WHEEL
pysat_kamodo-0.0.1.dist-info/top_level.txt
pysat_kamodo-0.0.1.dist-info/RECORD
