Metadata-Version: 2.1
Name: pysat-kamodo
Version: 0.0.1
Summary: Kamodo api for pysat
Home-page: https://pysat.github.io/pysatKamodo
Author: Asher Pembroke
Author-email: apembroke@gmail.com
License: NASA OPEN SOURCE AGREEMENT VERSION 1.3
Platform: UNKNOWN
Classifier: Programming Language :: Python :: 3.7
Classifier: Operating System :: OS Independent
Classifier: License :: OSI Approved
Requires-Python: >=3.6
Requires-Dist: pysat
Requires-Dist: kamodo
